social_auth/__init__.py
social_auth/apps.py
social_auth/plugin.py
social_auth/strategy.py
social_auth/utils.py
saleor_social_auth-0.6.0.dist-info/LICENSE
saleor_social_auth-0.6.0.dist-info/METADATA
saleor_social_auth-0.6.0.dist-info/WHEEL
saleor_social_auth-0.6.0.dist-info/entry_points.txt
saleor_social_auth-0.6.0.dist-info/top_level.txt
saleor_social_auth-0.6.0.dist-info/zip-safe
saleor_social_auth-0.6.0.dist-info/RECORD
